{
    "gpu_number": "1",
    "train_script": "main.py",
    "config_file_path": "train_config.json",

    "train_configs": 
    [
            {
                "optimizer": "adam",
                "lr": 0.0001,
                "batch_size": 2,
                "total_itrs": 30e3,
                "pretrained_backbone": false,
                "model": "deeplabv3plus_xception",
                "seed": 0,
                "crop_size": 512
            },
            {
                "optimizer": "fame",
                "lr": 0.0001,
                "batch_size": 2,
                "total_itrs": 30e3,
                "pretrained_backbone": false,
                "model": "deeplabv3plus_xception",
                "seed": 0,
                "crop_size": 512
            },
            {
                "optimizer": "sgd",
                "pretrained_backbone": false,
                "lr": 0.01,
                "batch_size": 2,
                "total_itrs": 30e3,
                "model": "deeplabv3plus_xception",
                "seed": 0,
                "crop_size": 512
            }
    ]
}